aiconfig/ChatCompletion.py
aiconfig/Config.py
aiconfig/__init__.py
aiconfig/callback.py
aiconfig/model_parser.py
aiconfig/registry.py
aiconfig/schema.py
aiconfig/test_inverse.py
aiconfig/default_parsers/__init__.py
aiconfig/default_parsers/anyscale_endpoint.py
aiconfig/default_parsers/dalle.py
aiconfig/default_parsers/hf.py
aiconfig/default_parsers/openai.py
aiconfig/default_parsers/palm.py
aiconfig/default_parsers/parameterized_model_parser.py
aiconfig/editor/__init__.py
aiconfig/editor/example_aiconfig_model_registry.py
aiconfig/editor/client/__init__.py
aiconfig/editor/client/node_modules/aiconfig/node_modules/flatted/python/flatted.py
aiconfig/editor/client/node_modules/aiconfig/node_modules/flatted/python/test.py
aiconfig/editor/client/node_modules/flatted/python/flatted.py
aiconfig/editor/client/node_modules/flatted/python/test.py
aiconfig/editor/server/__init__.py
aiconfig/editor/server/queue_iterator.py
aiconfig/editor/server/server.py
aiconfig/editor/server/server_utils.py
aiconfig/editor/server/static/asset-manifest.json
aiconfig/editor/server/static/index.html
aiconfig/editor/server/static/manifest.json
aiconfig/editor/server/static/robots.txt
aiconfig/editor/server/static/images/aiconfigLogo.png
aiconfig/editor/server/static/static/js/main.65ec2eba.js
aiconfig/editor/server/static/static/js/main.65ec2eba.js.LICENSE.txt
aiconfig/editor/server/static/static/js/main.65ec2eba.js.map
aiconfig/editor/server/static/static/js/main.7fca437d.js
aiconfig/editor/server/static/static/js/main.7fca437d.js.LICENSE.txt
aiconfig/editor/server/static/static/js/main.7fca437d.js.map
aiconfig/eval/__init__.py
aiconfig/eval/common.py
aiconfig/eval/lib.py
aiconfig/eval/metrics.py
aiconfig/eval/openai.py
aiconfig/eval/api/__init__.py
aiconfig/scripts/aiconfig_cli.py
aiconfig/scripts/run_aiconfig.py
aiconfig/scripts/rage/rage.py
aiconfig/util/__init__.py
aiconfig/util/config_utils.py
aiconfig/util/params.py
python_aiconfig_test-1.1.39.dist-info/LICENSE
python_aiconfig_test-1.1.39.dist-info/METADATA
python_aiconfig_test-1.1.39.dist-info/WHEEL
python_aiconfig_test-1.1.39.dist-info/entry_points.txt
python_aiconfig_test-1.1.39.dist-info/top_level.txt
python_aiconfig_test-1.1.39.dist-info/RECORD
