Metadata-Version: 2.1
Name: python-aiconfig-test
Version: 1.1.39
Summary: Python library for LastMile AI API
Author-email: Sarmad Qadri <sarmad@lastmileai.dev>
Project-URL: Homepage, https://github.com/lastmile-ai/aiconfig
Project-URL: Bug Tracker, https://github.com/lastmile-ai/aiconfig/issues
Classifier: Intended Audience :: Developers
Classifier: Programming Language :: Python :: 3
Requires-Python: >=3.7
License-File: LICENSE
Requires-Dist: black
Requires-Dist: flake8
Requires-Dist: flask-cors
Requires-Dist: flask[async]
Requires-Dist: frozendict
Requires-Dist: google-generativeai
Requires-Dist: huggingface-hub
Requires-Dist: hypothesis ==6.91.0
Requires-Dist: lastmile-utils ==0.0.21
Requires-Dist: mock
Requires-Dist: nest-asyncio
Requires-Dist: nltk
Requires-Dist: openai <1.5,>=1.0.0
Requires-Dist: prompt-toolkit
Requires-Dist: pybars3
Requires-Dist: pydantic >=2.1
Requires-Dist: pylint
Requires-Dist: pytest
Requires-Dist: pytest-asyncio
Requires-Dist: python-dotenv
Requires-Dist: pyyaml
Requires-Dist: requests
Requires-Dist: result
Requires-Dist: ruamel.yaml
